[
{"id":"1","name":"one","image":"https://via.placeholder.com/250x250", "discount_percentage":"25"}
,
{"id":"2","name":"two","image":"https://via.placeholder.com/250x250", "discount_percentage":"50"}
,
{"id":"3","name":"Atlantis the palm","image":"https://via.placeholder.com/250x250", "discount_percentage":"25"}
,
{"id":"4","name":"Atlantis the palm","image":"https://via.placeholder.com/250x250", "discount_percentage":"25"}
,
{"id":"5","name":"Atlantis the palm","image":"https://via.placeholder.com/250x250", "discount_percentage":"25"}
,
{"id":"6","name":"Atlantis the palm","image":"https://via.placeholder.com/250x250", "discount_percentage":"25"}
,
{"id":"7","name":"Atlantis the palm","image":"https://via.placeholder.com/250x250", "discount_percentage":"75"}
,
{"id":"8","name":"Atlantis the palm","image":"https://via.placeholder.com/250x250", "discount_percentage":"25"}
,
{"id":"9","name":"Atlantis the palm","image":"https://via.placeholder.com/250x250", "discount_percentage":"25"}
,
{"id":"10","name":"Atlantis the palm","image":"https://via.placeholder.com/250x250", "discount_percentage":"25"}
,
{"id":"11","name":"Atlantis the palm","image":"https://via.placeholder.com/250x250", "discount_percentage":"25"}
,
{"id":"12","name":"Atlantis the palm","image":"https://via.placeholder.com/250x250", "discount_percentage":"25"}
,
{"id":"13","name":"Atlantis the palm","image":"https://via.placeholder.com/250x250", "discount_percentage":"25"}
]